iris/__init__.py
iris-1.0.7.dist-info/LICENSE.txt
iris-1.0.7.dist-info/METADATA
iris-1.0.7.dist-info/WHEEL
iris-1.0.7.dist-info/top_level.txt
iris-1.0.7.dist-info/RECORD
