Metadata-Version: 2.1
Name: iris
Version: 1.0.7
Summary: A Python project for Illumon Iris
Home-page: https://deephaven.io/
Author: Deephaven Data Labs LLC
Author-email: python@deephaven.io
License: Apache 2.0
Keywords: Illumon Iris Deephaven
Platform: UNKNOWN
Classifier: Development Status :: 3 - Alpha
Classifier: Intended Audience :: Developers
Classifier: License :: OSI Approved :: Apache Software License
Classifier: Programming Language :: Python :: 2.7
Classifier: Programming Language :: Python :: 3
